{
  "fill" : {
    "automatic-gradient" : "display-p3:0.94039,0.90140,0.85549,1.00000",
    "orientation" : {
      "start" : {
        "x" : 0.5,
        "y" : 0
      },
      "stop" : {
        "x" : 0.5,
        "y" : 0.7
      }
    }
  },
  "groups" : [
    {
      "layers" : [
        {
          "glass" : true,
          "image-name" : "kangaroo.png",
          "name" : "kangaroo",
          "position" : {
            "scale" : 0.95,
            "translation-in-points" : [
              62.921875,
              0
            ]
          }
        }
      ],
      "shadow" : {
        "kind" : "neutral",
        "opacity" : 0.5
      },
      "translucency" : {
        "enabled" : true,
        "value" : 0.5
      }
    }
  ],
  "supported-platforms" : {
    "circles" : [
      "watchOS"
    ],
    "squares" : "shared"
  }
}